nonebot_plugin_mute/__init__.py
nonebot_plugin_mute/__main__.py
nonebot_plugin_mute/config.py
nonebot_plugin_mute-0.2.4.dist-info/LICENSE
nonebot_plugin_mute-0.2.4.dist-info/METADATA
nonebot_plugin_mute-0.2.4.dist-info/WHEEL
nonebot_plugin_mute-0.2.4.dist-info/RECORD
