Metadata-Version: 2.1
Name: nonebot_plugin_mute
Version: 0.2.4
Summary: 唔唔？你想被禁言嘛~？
Home-page: https://github.com/shengwang52005/nonebot_plugin_mute
License: MIT
Author: Miaowing
Author-email: shengwang52005@163.com
Requires-Python: >=3.10,<4.0
Classifier: License :: OSI Approved :: MIT License
Classifier: Programming Language :: Python :: 3
Classifier: Programming Language :: Python :: 3.10
Classifier: Programming Language :: Python :: 3.11
Classifier: Programming Language :: Python :: 3.12
Requires-Dist: nonebot-adapter-onebot (>=2.3.1)
Requires-Dist: nonebot2 (>=2.3.2)
Project-URL: Repository, https://github.com/shengwang52005/nonebot_plugin_mute
